xormxla_pd_comlumn/__init__.py
xormxla_pd_comlumn/example.py
example_pkg_xormxla_pd_columns-0.0.1.dist-info/LICENSE.txt
example_pkg_xormxla_pd_columns-0.0.1.dist-info/METADATA
example_pkg_xormxla_pd_columns-0.0.1.dist-info/WHEEL
example_pkg_xormxla_pd_columns-0.0.1.dist-info/top_level.txt
example_pkg_xormxla_pd_columns-0.0.1.dist-info/RECORD
