Metadata-Version: 2.1
Name: example-pkg-xormxla-pd-columns
Version: 0.0.1
Summary: xormxla sample lib
Author: xormxla
Author-email: xormxla21c@gmail.com
Classifier: Programming Language :: Python :: 3
Classifier: License :: OSI Approved :: MIT License
Classifier: Operating System :: OS Independent
Requires-Python: >=3
License-File: LICENSE.txt
